fences/__init__.py
fences/__main__.py
fences/agent.py
fences/cli.py
fences_api-0.1.3.dist-info/METADATA
fences_api-0.1.3.dist-info/WHEEL
fences_api-0.1.3.dist-info/entry_points.txt
fences_api-0.1.3.dist-info/licenses/LICENSE
fences_api-0.1.3.dist-info/RECORD
